condate.py
Condate-0.1.dist-info/LICENSE
Condate-0.1.dist-info/METADATA
Condate-0.1.dist-info/WHEEL
Condate-0.1.dist-info/entry_points.txt
Condate-0.1.dist-info/top_level.txt
Condate-0.1.dist-info/RECORD
