Metadata-Version: 2.1
Name: Condate
Version: 0.1
Summary: A simple date conversion script
Home-page: https://twitter.com/Lanaev0li
Author: Avinion
Author-email: shizofrin@gmail.com
License: Avinion Group
Classifier: Programming Language :: Python :: 3
Classifier: License :: OSI Approved :: MIT License
Classifier: Operating System :: OS Independent
Requires-Python: >=3.6
License-File: LICENSE
